{
 "name": "25 84",
 "relations": [
  {"name": "ci", "aliastable": "cast_info", "basetable": "cast_info", "cardinality": 36244344, "unfilteredCardinality": 36244344},
  {"name": "it1", "aliastable": "info_type", "basetable": "info_type", "cardinality": 21, "unfilteredCardinality": 113},
  {"name": "it2", "aliastable": "info_type2", "basetable": "info_type", "cardinality": 6, "unfilteredCardinality": 113},
  {"name": "k", "aliastable": "keyword", "basetable": "keyword", "cardinality": 168, "unfilteredCardinality": 134170},
  {"name": "mi", "aliastable": "movie_info", "basetable": "movie_info", "cardinality": 164836, "unfilteredCardinality": 14835720},
  {"name": "mi_idx", "aliastable": "movie_info_idx", "basetable": "movie_info_idx", "cardinality": 1380035, "unfilteredCardinality": 1380035},
  {"name": "mk", "aliastable": "movie_keyword", "basetable": "movie_keyword", "cardinality": 4523930, "unfilteredCardinality": 4523930},
  {"name": "n", "aliastable": "name", "basetable": "name", "cardinality": 4167491, "unfilteredCardinality": 4167491},
  {"name": "t", "aliastable": "title", "basetable": "title", "cardinality": 8101, "unfilteredCardinality": 2528312}
 ],
 "joins": [
  {"relations": ["t", "mi"]},
  {"relations": ["t", "mi_idx"]},
  {"relations": ["t", "ci"]},
  {"relations": ["t", "mk"]},
  {"relations": ["ci", "mi"]},
  {"relations": ["ci", "mi_idx"]},
  {"relations": ["ci", "mk"]},
  {"relations": ["mi", "mi_idx"]},
  {"relations": ["mi", "mk"]},
  {"relations": ["mi_idx", "mk"]},
  {"relations": ["n", "ci"]},
  {"relations": ["it1", "mi"]},
  {"relations": ["it2", "mi_idx"]},
  {"relations": ["k", "mk"]}
 ],
 "sizes": [
  {"relations": ["ci", "mi"], "cardinality": 2729048},
  {"relations": ["ci", "mi_idx"], "cardinality": 40911741},
  {"relations": ["ci", "mk"], "cardinality": 215765477},
  {"relations": ["ci", "n"], "cardinality": 36244344},
  {"relations": ["ci", "t"], "cardinality": 123049},
  {"relations": ["it1", "mi"], "cardinality": 164769},
  {"relations": ["it2", "mi_idx"], "cardinality": 0},
  {"relations": ["k", "mk"], "cardinality": 8293},
  {"relations": ["mi", "mi_idx"], "cardinality": 128802},
  {"relations": ["mi", "mk"], "cardinality": 574242},
  {"relations": ["mi", "t"], "cardinality": 467},
  {"relations": ["mi_idx", "mk"], "cardinality": 10424626},
  {"relations": ["mi_idx", "t"], "cardinality": 5296},
  {"relations": ["mk", "t"], "cardinality": 15471},
  {"relations": ["ci", "it1", "mi"], "cardinality": 2724258},
  {"relations": ["ci", "it2", "mi_idx"], "cardinality": 0},
  {"relations": ["ci", "k", "mk"], "cardinality": 482495},
  {"relations": ["ci", "mi", "mi_idx"], "cardinality": 4284359},
  {"relations": ["ci", "mi", "mk"], "cardinality": 39440356},
  {"relations": ["ci", "mi", "n"], "cardinality": 2673240},
  {"relations": ["ci", "mi", "t"], "cardinality": 9218},
  {"relations": ["ci", "mi_idx", "mk"], "cardinality": 607273961},
  {"relations": ["ci", "mi_idx", "n"], "cardinality": 349419},
  {"relations": ["ci", "mi_idx", "t"], "cardinality": 158714},
  {"relations": ["ci", "mk", "n"], "cardinality": 203347},
  {"relations": ["ci", "mk", "t"], "cardinality": 765190},
  {"relations": ["ci", "n", "t"], "cardinality": 123049},
  {"relations": ["it1", "mi", "mi_idx"], "cardinality": 128594},
  {"relations": ["it1", "mi", "mk"], "cardinality": 568885},
  {"relations": ["it1", "mi", "t"], "cardinality": 467},
  {"relations": ["it2", "mi", "mi_idx"], "cardinality": 0},
  {"relations": ["it2", "mi_idx", "mk"], "cardinality": 0},
  {"relations": ["it2", "mi_idx", "t"], "cardinality": 0},
  {"relations": ["k", "mi", "mk"], "cardinality": 1275},
  {"relations": ["k", "mi_idx", "mk"], "cardinality": 21376},
  {"relations": ["k", "mk", "t"], "cardinality": 19},
  {"relations": ["mi", "mi_idx", "mk"], "cardinality": 1528698},
  {"relations": ["mi", "mi_idx", "t"], "cardinality": 477},
  {"relations": ["mi", "mk", "t"], "cardinality": 2217},
  {"relations": ["mi_idx", "mk", "t"], "cardinality": 34544},
  {"relations": ["ci", "it1", "mi", "mi_idx"], "cardinality": 4269060},
  {"relations": ["ci", "it1", "mi", "mk"], "cardinality": 39024424},
  {"relations": ["ci", "it1", "mi", "n"], "cardinality": 1322992},
  {"relations": ["ci", "it1", "mi", "t"], "cardinality": 9218},
  {"relations": ["ci", "it2", "mi", "mi_idx"], "cardinality": 0},
  {"relations": ["ci", "it2", "mi_idx", "mk"], "cardinality": 0},
  {"relations": ["ci", "it2", "mi_idx", "n"], "cardinality": 0},
  {"relations": ["ci", "it2", "mi_idx", "t"], "cardinality": 0},
  {"relations": ["ci", "k", "mi", "mk"], "cardinality": 110129},
  {"relations": ["ci", "k", "mi_idx", "mk"], "cardinality": 1409228},
  {"relations": ["ci", "k", "mk", "n"], "cardinality": 334150},
  {"relations": ["ci", "k", "mk", "t"], "cardinality": 1214},
  {"relations": ["ci", "mi", "mi_idx", "mk"], "cardinality": 116201919},
  {"relations": ["ci", "mi", "mi_idx", "n"], "cardinality": 4127718},
  {"relations": ["ci", "mi", "mi_idx", "t"], "cardinality": 17124},
  {"relations": ["ci", "mi", "mk", "n"], "cardinality": 38685934},
  {"relations": ["ci", "mi", "mk", "t"], "cardinality": 233233},
  {"relations": ["ci", "mi", "n", "t"], "cardinality": 9218},
  {"relations": ["ci", "mi_idx", "mk", "n"], "cardinality": 164088},
  {"relations": ["ci", "mi_idx", "mk", "t"], "cardinality": 2177302},
  {"relations": ["ci", "mi_idx", "n", "t"], "cardinality": 158714},
  {"relations": ["ci", "mk", "n", "t"], "cardinality": 765190},
  {"relations": ["it1", "it2", "mi", "mi_idx"], "cardinality": 0},
  {"relations": ["it1", "k", "mi", "mk"], "cardinality": 1260},
  {"relations": ["it1", "mi", "mi_idx", "mk"], "cardinality": 1511523},
  {"relations": ["it1", "mi", "mi_idx", "t"], "cardinality": 477},
  {"relations": ["it1", "mi", "mk", "t"], "cardinality": 2217},
  {"relations": ["it2", "k", "mi_idx", "mk"], "cardinality": 0},
  {"relations": ["it2", "mi", "mi_idx", "mk"], "cardinality": 0},
  {"relations": ["it2", "mi", "mi_idx", "t"], "cardinality": 0},
  {"relations": ["it2", "mi_idx", "mk", "t"], "cardinality": 0},
  {"relations": ["k", "mi", "mi_idx", "mk"], "cardinality": 3628},
  {"relations": ["k", "mi", "mk", "t"], "cardinality": 3},
  {"relations": ["k", "mi_idx", "mk", "t"], "cardinality": 57},
  {"relations": ["mi", "mi_idx", "mk", "t"], "cardinality": 6114},
  {"relations": ["ci", "it1", "it2", "mi", "mi_idx"], "cardinality": 0},
  {"relations": ["ci", "it1", "k", "mi", "mk"], "cardinality": 108533},
  {"relations": ["ci", "it1", "mi", "mi_idx", "mk"], "cardinality": 114810707},
  {"relations": ["ci", "it1", "mi", "mi_idx", "n"], "cardinality": 4046641},
  {"relations": ["ci", "it1", "mi", "mi_idx", "t"], "cardinality": 17124},
  {"relations": ["ci", "it1", "mi", "mk", "n"], "cardinality": 30847679},
  {"relations": ["ci", "it1", "mi", "mk", "t"], "cardinality": 233233},
  {"relations": ["ci", "it1", "mi", "n", "t"], "cardinality": 9218},
  {"relations": ["ci", "it2", "k", "mi_idx", "mk"], "cardinality": 0},
  {"relations": ["ci", "it2", "mi", "mi_idx", "mk"], "cardinality": 0},
  {"relations": ["ci", "it2", "mi", "mi_idx", "n"], "cardinality": 0},
  {"relations": ["ci", "it2", "mi", "mi_idx", "t"], "cardinality": 0},
  {"relations": ["ci", "it2", "mi_idx", "mk", "n"], "cardinality": 0},
  {"relations": ["ci", "it2", "mi_idx", "mk", "t"], "cardinality": 0},
  {"relations": ["ci", "it2", "mi_idx", "n", "t"], "cardinality": 0},
  {"relations": ["ci", "k", "mi", "mi_idx", "mk"], "cardinality": 329184},
  {"relations": ["ci", "k", "mi", "mk", "n"], "cardinality": 79580},
  {"relations": ["ci", "k", "mi", "mk", "t"], "cardinality": 310},
  {"relations": ["ci", "k", "mi_idx", "mk", "n"], "cardinality": 1060794},
  {"relations": ["ci", "k", "mi_idx", "mk", "t"], "cardinality": 3642},
  {"relations": ["ci", "k", "mk", "n", "t"], "cardinality": 1214},
  {"relations": ["ci", "mi", "mi_idx", "mk", "n"], "cardinality": 113315439},
  {"relations": ["ci", "mi", "mi_idx", "mk", "t"], "cardinality": 693615},
  {"relations": ["ci", "mi", "mi_idx", "n", "t"], "cardinality": 17124},
  {"relations": ["ci", "mi", "mk", "n", "t"], "cardinality": 233233},
  {"relations": ["ci", "mi_idx", "mk", "n", "t"], "cardinality": 2177302},
  {"relations": ["it1", "it2", "mi", "mi_idx", "mk"], "cardinality": 0},
  {"relations": ["it1", "it2", "mi", "mi_idx", "t"], "cardinality": 0},
  {"relations": ["it1", "k", "mi", "mi_idx", "mk"], "cardinality": 3577},
  {"relations": ["it1", "k", "mi", "mk", "t"], "cardinality": 3},
  {"relations": ["it1", "mi", "mi_idx", "mk", "t"], "cardinality": 6114},
  {"relations": ["it2", "k", "mi", "mi_idx", "mk"], "cardinality": 0},
  {"relations": ["it2", "k", "mi_idx", "mk", "t"], "cardinality": 0},
  {"relations": ["it2", "mi", "mi_idx", "mk", "t"], "cardinality": 0},
  {"relations": ["k", "mi", "mi_idx", "mk", "t"], "cardinality": 9},
  {"relations": ["ci", "it1", "it2", "mi", "mi_idx", "mk"], "cardinality": 0},
  {"relations": ["ci", "it1", "it2", "mi", "mi_idx", "n"], "cardinality": 0},
  {"relations": ["ci", "it1", "it2", "mi", "mi_idx", "t"], "cardinality": 0},
  {"relations": ["ci", "it1", "k", "mi", "mi_idx", "mk"], "cardinality": 323472},
  {"relations": ["ci", "it1", "k", "mi", "mk", "n"], "cardinality": 100124},
  {"relations": ["ci", "it1", "k", "mi", "mk", "t"], "cardinality": 310},
  {"relations": ["ci", "it1", "mi", "mi_idx", "mk", "n"], "cardinality": 694153},
  {"relations": ["ci", "it1", "mi", "mi_idx", "mk", "t"], "cardinality": 693615},
  {"relations": ["ci", "it1", "mi", "mi_idx", "n", "t"], "cardinality": 17124},
  {"relations": ["ci", "it1", "mi", "mk", "n", "t"], "cardinality": 233233},
  {"relations": ["ci", "it2", "k", "mi", "mi_idx", "mk"], "cardinality": 0},
  {"relations": ["ci", "it2", "k", "mi_idx", "mk", "n"], "cardinality": 0},
  {"relations": ["ci", "it2", "k", "mi_idx", "mk", "t"], "cardinality": 0},
  {"relations": ["ci", "it2", "mi", "mi_idx", "mk", "n"], "cardinality": 0},
  {"relations": ["ci", "it2", "mi", "mi_idx", "mk", "t"], "cardinality": 0},
  {"relations": ["ci", "it2", "mi", "mi_idx", "n", "t"], "cardinality": 0},
  {"relations": ["ci", "it2", "mi_idx", "mk", "n", "t"], "cardinality": 0},
  {"relations": ["ci", "k", "mi", "mi_idx", "mk", "n"], "cardinality": 329184},
  {"relations": ["ci", "k", "mi", "mi_idx", "mk", "t"], "cardinality": 930},
  {"relations": ["ci", "k", "mi", "mk", "n", "t"], "cardinality": 310},
  {"relations": ["ci", "k", "mi_idx", "mk", "n", "t"], "cardinality": 3642},
  {"relations": ["ci", "mi", "mi_idx", "mk", "n", "t"], "cardinality": 693615},
  {"relations": ["it1", "it2", "k", "mi", "mi_idx", "mk"], "cardinality": 0},
  {"relations": ["it1", "it2", "mi", "mi_idx", "mk", "t"], "cardinality": 0},
  {"relations": ["it1", "k", "mi", "mi_idx", "mk", "t"], "cardinality": 9},
  {"relations": ["it2", "k", "mi", "mi_idx", "mk", "t"], "cardinality": 0},
  {"relations": ["ci", "it1", "it2", "k", "mi", "mi_idx", "mk"], "cardinality": 0},
  {"relations": ["ci", "it1", "it2", "mi", "mi_idx", "mk", "n"], "cardinality": 0},
  {"relations": ["ci", "it1", "it2", "mi", "mi_idx", "mk", "t"], "cardinality": 0},
  {"relations": ["ci", "it1", "it2", "mi", "mi_idx", "n", "t"], "cardinality": 0},
  {"relations": ["ci", "it1", "k", "mi", "mi_idx", "mk", "n"], "cardinality": 288452},
  {"relations": ["ci", "it1", "k", "mi", "mi_idx", "mk", "t"], "cardinality": 930},
  {"relations": ["ci", "it1", "k", "mi", "mk", "n", "t"], "cardinality": 310},
  {"relations": ["ci", "it1", "mi", "mi_idx", "mk", "n", "t"], "cardinality": 693615},
  {"relations": ["ci", "it2", "k", "mi", "mi_idx", "mk", "n"], "cardinality": 0},
  {"relations": ["ci", "it2", "k", "mi", "mi_idx", "mk", "t"], "cardinality": 0},
  {"relations": ["ci", "it2", "k", "mi_idx", "mk", "n", "t"], "cardinality": 0},
  {"relations": ["ci", "it2", "mi", "mi_idx", "mk", "n", "t"], "cardinality": 0},
  {"relations": ["ci", "k", "mi", "mi_idx", "mk", "n", "t"], "cardinality": 930},
  {"relations": ["it1", "it2", "k", "mi", "mi_idx", "mk", "t"], "cardinality": 0},
  {"relations": ["ci", "it1", "it2", "k", "mi", "mi_idx", "mk", "n"], "cardinality": 0},
  {"relations": ["ci", "it1", "it2", "k", "mi", "mi_idx", "mk", "t"], "cardinality": 0},
  {"relations": ["ci", "it1", "it2", "mi", "mi_idx", "mk", "n", "t"], "cardinality": 0},
  {"relations": ["ci", "it1", "k", "mi", "mi_idx", "mk", "n", "t"], "cardinality": 930},
  {"relations": ["ci", "it2", "k", "mi", "mi_idx", "mk", "n", "t"], "cardinality": 0},
  {"relations": ["ci", "it1", "it2", "k", "mi", "mi_idx", "mk", "n", "t"], "cardinality": 0}
 ],
 "query": "SELECT MIN(mi.info) AS movie_budget, MIN(mi_idx.info) AS movie_votes, MIN(n.name) AS male_writer, MIN(t.title) AS violent_movie_title FROM cast_info AS ci, info_type AS it1, info_type AS it2, keyword AS k, movie_info AS mi, movie_info_idx AS mi_idx, movie_keyword AS mk, name AS n, title AS t WHERE t.id = mi.movie_id AND t.id = mi_idx.movie_id AND t.id = ci.movie_id AND t.id = mk.movie_id AND ci.movie_id = mi.movie_id AND ci.movie_id = mi_idx.movie_id AND ci.movie_id = mk.movie_id AND mi.movie_id = mi_idx.movie_id AND mi.movie_id = mk.movie_id AND mi_idx.movie_id = mk.movie_id AND n.id = ci.person_id AND it1.id = mi.info_type_id AND it2.id = mi_idx.info_type_id AND k.id = mk.keyword_id AND it1.info in ('LD release country','LD catalog number','death date','LD length','screenplay-teleplay','LD color information','LD video noise','color info','LD certification','opening weekend','LD disc format','taglines','mpaa','keywords','languages','interviews','birth date','LD supplement','rentals','sound mix','LD release date') AND mi.info in ('Filipino','Faroese','Norwegian','Welsh','French','Hungarian','Spanish') AND it2.info not in ('mini biography','books','keywords','LD sharpness','book','article') AND (k.keyword like '%journey%' OR k.keyword like '%terrorist%' OR k.keyword like '%escape%') AND (t.title like '%spaceship%' OR t.title like '%pen%' OR t.title like '%door%' OR t.title like '%clock%')",
 "join columns": ["it1.id", "mk.keyword_id", "mk.movie_id", "k.id", "ci.movie_id", "n.id", "mi.info_type_id", "t.id", "mi_idx.movie_id", "ci.person_id", "mi.movie_id", "mi_idx.info_type_id", "it2.id"],
 "unary columns": ["it2.info", "it1.info", "t.title", "k.keyword", "mi.info"],
 "join expressions": [{"left": "t.id", "right": "mi.movie_id"}, {"left": "t.id", "right": "mi_idx.movie_id"}, {"left": "t.id", "right": "ci.movie_id"}, {"left": "t.id", "right": "mk.movie_id"}, {"left": "ci.movie_id", "right": "mi.movie_id"}, {"left": "ci.movie_id", "right": "mi_idx.movie_id"}, {"left": "ci.movie_id", "right": "mk.movie_id"}, {"left": "mi.movie_id", "right": "mi_idx.movie_id"}, {"left": "mi.movie_id", "right": "mk.movie_id"}, {"left": "mi_idx.movie_id", "right": "mk.movie_id"}, {"left": "n.id", "right": "ci.person_id"}, {"left": "it1.id", "right": "mi.info_type_id"}, {"left": "it2.id", "right": "mi_idx.info_type_id"}, {"left": "k.id", "right": "mk.keyword_id"}],
 "left deep tree min cost": "0",
 "left deep tree min order": "((((((((it2 join mi_idx) join ci) join it1) join k) join mi) join mk) join n) join t)",
 "bushy deep tree min cost": "0",
 "bushy deep tree min order": "((((((((it2 join mi_idx) join ci) join it1) join k) join mi) join mk) join n) join t)"
}